{
    "emit_debug_impls": true,
    "encode_trait_path": "::fidl_next::fuchsia::HandleEncoder",
    "decode_trait_path": "::fidl_next::fuchsia::HandleDecoder",
    "crate_prefix": "fidl_next",
    "resource_bindings": {
        "handles": {
            "fdf/handle": {
                "wire_path_template": "::fdf_fidl::wire::DriverChannel",
                "optional_wire_path_template": "::fdf_fidl::wire::OptionalDriverChannel",
                "natural_path_template": "::fdf_fidl::DriverChannel"
            },
            "zx/Handle": {
                "wire_path_template": "::fidl_next::wire::fuchsia::{subtype}",
                "optional_wire_path_template": "::fidl_next::wire::fuchsia::Optional{subtype}",
                "natural_path_template": "::fidl_next::fuchsia::zx::{subtype}"
            }
        },
        "default_handle": "zx/Handle",
        "endpoints": {
            "Channel": {
                "wire_path": "::fidl_next::wire::fuchsia::Channel",
                "optional_wire_path": "::fidl_next::wire::fuchsia::OptionalChannel",
                "natural_path": "::fidl_next::fuchsia::zx::Channel"
            },
            "Driver": {
                "wire_path": "::fdf_fidl::wire::DriverChannel",
                "optional_wire_path": "::fdf_fidl::wire::OptionalDriverChannel",
                "natural_path": "::fdf_fidl::DriverChannel"
            }
        },
        "default_endpoint": "Channel"
    }
}
